froggius/__init__.py
froggius/logger.py
froggius-0.1.7.dist-info/LICENSE
froggius-0.1.7.dist-info/METADATA
froggius-0.1.7.dist-info/WHEEL
froggius-0.1.7.dist-info/top_level.txt
froggius-0.1.7.dist-info/RECORD
