Metadata-Version: 2.1
Name: froggius
Version: 0.1.7
Summary: Froggius is a lightweight and dumb easy logging libary for python
Home-page: https://github.com/zlElo/Froggius
Author: zlElo
Author-email: mail@zlelo.de
License: MPL-2.0
Keywords: logging,logger,easy-to-use,log
Classifier: Intended Audience :: Developers
Classifier: Programming Language :: Python :: 3
Classifier: Operating System :: Unix
Classifier: Operating System :: MacOS :: MacOS X
Classifier: Operating System :: Microsoft :: Windows
License-File: LICENSE
